geeagri/__init__.py
geeagri/analysis.py
geeagri/common.py
geeagri/extract.py
geeagri/geeagri.py
geeagri/phenology.py
geeagri/preprocessing.py
geeagri-1.0.0.dist-info/licenses/LICENSE
geeagri-1.0.0.dist-info/METADATA
geeagri-1.0.0.dist-info/WHEEL
geeagri-1.0.0.dist-info/entry_points.txt
geeagri-1.0.0.dist-info/top_level.txt
geeagri-1.0.0.dist-info/RECORD
