Metadata-Version: 2.4
Name: geeagri
Version: 1.0.0
Summary: Python tools for agricultural analysis powered by Google Earth Engine.
Author-email: Krishnagopal Halder <geonextgis@gmail.com>
License: MIT License
Project-URL: Homepage, https://github.com/geonextgis/geeagri
Keywords: geeagri
Classifier: Intended Audience :: Developers
Classifier: License :: OSI Approved :: MIT License
Classifier: Natural Language :: English
Classifier: Programming Language :: Python :: 3.8
Classifier: Programming Language :: Python :: 3.9
Classifier: Programming Language :: Python :: 3.10
Classifier: Programming Language :: Python :: 3.11
Classifier: Programming Language :: Python :: 3.12
Requires-Python: >=3.8
License-File: LICENSE
Requires-Dist: earthengine-api
Requires-Dist: geemap
Requires-Dist: geopandas
Requires-Dist: matplotlib
Requires-Dist: numpy
Requires-Dist: pandas
Requires-Dist: pillow
Requires-Dist: rasterio
Requires-Dist: retry
Provides-Extra: all
Requires-Dist: geeagri[extra]; extra == "all"
Provides-Extra: extra
Requires-Dist: pandas; extra == "extra"
Dynamic: license-file
